<WhiteboardCaptureSession>
	<WhiteboardDescription>
		<SensorLocation corner="top_left" />
		<DiagonallyOppositeCoords x="400" y="524.6176268861454" />
		<VerticallyOppositeCoords x="25.0" y="524.6176268861454" />
		<HorizontallyOppositeCoords x="400" y="39.35528120713306" />
	</WhiteboardDescription>
	<StrokeSet>
		<Stroke colour="black">
			<Point x="165.0" y="14.617626886145418" />
			<Point x="157.53257887517142" y="23.588820301783358" />
			<Point x="152.57544581618657" y="32.776063100137165" />
			<Point x="150.0462962962963" y="41.83984910836763" />
			<Point x="149.8628257887517" y="50.44067215363512" />
			<Point x="151.94272976680384" y="58.23902606310014" />
			<Point x="156.2037037037037" y="64.89540466392327" />
			<Point x="162.56344307270234" y="70.07030178326474" />
			<Point x="170.93964334705075" y="73.42421124828542" />
			<Point x="181.25" y="74.61762688614542" />
			<Point x="181.25" y="74.61762688614542" />
			<Point x="190.75102880658432" y="73.54595336076828" />
			<Point x="199.94341563786008" y="70.48868312757207" />
			<Point x="208.61111111111114" y="65.68244170096023" />
			<Point x="216.5380658436214" y="59.363854595336115" />
			<Point x="223.5082304526749" y="51.7695473251029" />
			<Point x="229.30555555555551" y="43.13614540466397" />
			<Point x="233.71399176954733" y="33.70027434842257" />
			<Point x="236.51748971193416" y="23.69855967078195" />
			<Point x="237.5" y="13.367626886145418" />
			<Point x="237.5" y="13.367626886145418" />
			<Point x="235.631001371742" y="7.854938271605079" />
			<Point x="230.5109739368999" y="3.803155006858674" />
			<Point x="222.87037037037038" y="1.191700960219464" />
			<Point x="213.43964334705078" y="0.0" />
			<Point x="202.94924554183814" y="0.20747599451297563" />
			<Point x="192.12962962962962" y="1.7935528120713684" />
			<Point x="181.71124828532237" y="4.73765432098773" />
			<Point x="172.42455418381343" y="9.019204389574755" />
			<Point x="165.0" y="14.617626886145418" />
			<Point x="165.0" y="14.617626886145418" />
			<Point x="165.0" y="14.617626886145418" />
			<Point x="165.0" y="14.617626886145418" />
			<Point x="165.0" y="14.617626886145418" />
			<Point x="165.0" y="14.617626886145418" />
			<Point x="165.0" y="14.617626886145418" />
			<Point x="165.0" y="14.617626886145418" />
			<Point x="165.0" y="14.617626886145418" />
			<Point x="165.0" y="14.617626886145418" />
			<Point x="165.0" y="14.617626886145418" />
		</Stroke>
		<Stroke colour="black">
			<Point x="193.75" y="173.36762688614544" />
			<Point x="170.18518518518513" y="183.38477366255162" />
			<Point x="145.2314814814815" y="199.24554183813441" />
			<Point x="120.00000000000004" y="219.6639231824417" />
			<Point x="95.60185185185188" y="243.35390946502056" />
			<Point x="73.14814814814815" y="269.0294924554184" />
			<Point x="53.75" y="295.40466392318245" />
			<Point x="38.518518518518526" y="321.1934156378601" />
			<Point x="28.56481481481482" y="345.10973936899865" />
			<Point x="25.0" y="365.86762688614544" />
			<Point x="25.0" y="365.86762688614544" />
			<Point x="27.762345679012345" y="383.5270919067216" />
			<Point x="35.617283950617285" y="398.0692729766804" />
			<Point x="47.91666666666667" y="409.3398491083676" />
			<Point x="64.01234567901234" y="417.184499314129" />
			<Point x="83.25617283950616" y="421.44890260631" />
			<Point x="104.99999999999997" y="421.9787379972566" />
			<Point x="128.59567901234564" y="418.61968449931413" />
			<Point x="153.39506172839504" y="411.2174211248286" />
			<Point x="178.75" y="399.61762688614544" />
			<Point x="178.75" y="399.61762688614544" />
			<Point x="186.96673525377224" y="395.13888888888897" />
			<Point x="194.8542524005487" y="390.91735253772293" />
			<Point x="202.26851851851853" y="387.02503429355284" />
			<Point x="209.06550068587103" y="383.533950617284" />
			<Point x="215.10116598079557" y="380.51611796982166" />
			<Point x="220.23148148148144" y="378.0435528120714" />
			<Point x="224.312414266118" y="376.1882716049383" />
			<Point x="227.1999314128944" y="375.0222908093279" />
			<Point x="228.75" y="374.61762688614544" />
			<Point x="228.75" y="374.61762688614544" />
			<Point x="229.2524005486968" y="375.24862825788756" />
			<Point x="229.89883401920443" y="377.07304526748976" />
			<Point x="230.64814814814818" y="379.9879972565158" />
			<Point x="231.45919067215362" y="383.8906035665295" />
			<Point x="232.29080932784638" y="388.67798353909467" />
			<Point x="233.10185185185182" y="394.24725651577506" />
			<Point x="233.85116598079563" y="400.49554183813444" />
			<Point x="234.49759945130313" y="407.3199588477367" />
			<Point x="235.0" y="414.61762688614544" />
			<Point x="235.0" y="414.61762688614544" />
			<Point x="236.89814814814812" y="431.00994513031554" />
			<Point x="240.0925925925926" y="445.2006172839507" />
			<Point x="244.58333333333334" y="457.21021947873805" />
			<Point x="250.37037037037038" y="467.0593278463649" />
			<Point x="257.4537037037037" y="474.7685185185186" />
			<Point x="265.8333333333333" y="480.3583676268862" />
			<Point x="275.50925925925924" y="483.84945130315504" />
			<Point x="286.4814814814814" y="485.26234567901236" />
			<Point x="298.75" y="484.61762688614544" />
			<Point x="298.75" y="484.61762688614544" />
			<Point x="312.3405349794238" y="481.67181069958855" />
			<Point x="323.0298353909465" y="476.6066529492456" />
			<Point x="330.69444444444446" y="470.08058984910843" />
			<Point x="335.2109053497942" y="462.75205761316874" />
			<Point x="336.45576131687244" y="455.27949245541845" />
			<Point x="334.30555555555554" y="448.32133058984914" />
			<Point x="328.63683127572017" y="442.5360082304527" />
			<Point x="319.32613168724276" y="438.5819615912209" />
			<Point x="306.25" y="437.11762688614544" />
			<Point x="306.25" y="437.11762688614544" />
			<Point x="302.6388888888889" y="437.11762688614544" />
			<Point x="299.02777777777777" y="437.11762688614544" />
			<Point x="295.4166666666667" y="437.11762688614544" />
			<Point x="291.80555555555554" y="437.11762688614544" />
			<Point x="288.19444444444446" y="437.11762688614544" />
			<Point x="284.5833333333333" y="437.11762688614544" />
			<Point x="280.97222222222223" y="437.11762688614544" />
			<Point x="277.3611111111111" y="437.11762688614544" />
			<Point x="273.75" y="437.11762688614544" />
			<Point x="273.75" y="437.11762688614544" />
			<Point x="274.72222222222223" y="426.0065157750343" />
			<Point x="275.69444444444446" y="414.8954046639232" />
			<Point x="276.6666666666667" y="403.78429355281213" />
			<Point x="277.6388888888889" y="392.673182441701" />
			<Point x="278.6111111111111" y="381.56207133058984" />
			<Point x="279.5833333333333" y="370.45096021947876" />
			<Point x="280.55555555555554" y="359.3398491083676" />
			<Point x="281.52777777777777" y="348.22873799725653" />
			<Point x="282.5" y="337.1176268861454" />
			<Point x="282.5" y="337.1176268861454" />
			<Point x="284.6227709190672" y="311.25000000000006" />
			<Point x="285.9636488340192" y="289.991426611797" />
			<Point x="286.4814814814815" y="272.85836762688615" />
			<Point x="286.1351165980796" y="259.3672839506173" />
			<Point x="284.883401920439" y="249.0346364883402" />
			<Point x="282.68518518518516" y="241.37688614540474" />
			<Point x="279.49931412894375" y="235.9104938271605" />
			<Point x="275.2846364883402" y="232.1519204389575" />
			<Point x="270.0" y="229.61762688614544" />
			<Point x="270.0" y="229.61762688614544" />
			<Point x="266.35116598079554" y="228.0126886145405" />
			<Point x="262.93895747599447" y="225.75960219478736" />
			<Point x="259.81481481481484" y="222.95096021947876" />
			<Point x="257.0301783264746" y="219.67935528120714" />
			<Point x="254.63648834019205" y="216.03737997256516" />
			<Point x="252.68518518518516" y="212.11762688614544" />
			<Point x="251.22770919067216" y="208.01268861454048" />
			<Point x="250.31550068587103" y="203.81515775034302" />
			<Point x="250.0" y="199.61762688614544" />
			<Point x="250.0" y="199.61762688614544" />
			<Point x="249.22325102880654" y="191.47462277091918" />
			<Point x="246.9341563786008" y="184.5661865569273" />
			<Point x="243.19444444444449" y="178.92318244170093" />
			<Point x="238.0658436213992" y="174.57647462277097" />
			<Point x="231.61008230452677" y="171.55692729766807" />
			<Point x="223.8888888888889" y="169.8954046639233" />
			<Point x="214.96399176954733" y="169.62277091906728" />
			<Point x="204.8971193415638" y="170.76989026063103" />
			<Point x="193.75" y="173.36762688614544" />
			<Point x="193.75" y="173.36762688614544" />
			<Point x="193.75" y="173.36762688614544" />
			<Point x="193.75" y="173.36762688614544" />
			<Point x="193.75" y="173.36762688614544" />
			<Point x="193.75" y="173.36762688614544" />
			<Point x="193.75" y="173.36762688614544" />
			<Point x="193.75" y="173.36762688614544" />
			<Point x="193.75" y="173.36762688614544" />
			<Point x="193.75" y="173.36762688614544" />
			<Point x="193.75" y="173.36762688614544" />
			<Point x="200.0" y="243.36762688614544" />
			<Point x="200.0" y="243.36762688614544" />
			<Point x="200.0" y="243.36762688614544" />
			<Point x="200.0" y="243.36762688614544" />
			<Point x="200.0" y="243.36762688614544" />
			<Point x="200.0" y="243.36762688614544" />
			<Point x="200.0" y="243.36762688614544" />
			<Point x="200.0" y="243.36762688614544" />
			<Point x="200.0" y="243.36762688614544" />
			<Point x="200.0" y="243.36762688614544" />
			<Point x="200.0" y="243.36762688614544" />
			<Point x="200.22290809327842" y="246.6443758573389" />
			<Point x="200.85733882030178" y="249.76680384087788" />
			<Point x="201.85185185185188" y="252.673182441701" />
			<Point x="203.15500685871055" y="255.3017832647463" />
			<Point x="204.71536351165986" y="257.59087791495205" />
			<Point x="206.48148148148144" y="259.4787379972566" />
			<Point x="208.4019204389575" y="260.90363511659814" />
			<Point x="210.42524005486968" y="261.803840877915" />
			<Point x="212.5" y="262.11762688614544" />
			<Point x="212.5" y="262.11762688614544" />
			<Point x="214.90397805212615" y="262.38854595336085" />
			<Point x="217.10219478738" y="263.1738683127572" />
			<Point x="219.07407407407408" y="264.4324417009602" />
			<Point x="220.79903978052124" y="266.1231138545953" />
			<Point x="222.25651577503427" y="268.2047325102881" />
			<Point x="223.42592592592592" y="270.636145404664" />
			<Point x="224.28669410150889" y="273.3762002743485" />
			<Point x="224.81824417009597" y="276.3837448559671" />
			<Point x="225.0" y="279.61762688614544" />
			<Point x="225.0" y="279.61762688614544" />
			<Point x="222.037037037037" y="290.1183127572017" />
			<Point x="213.8888888888889" y="302.69718792866945" />
			<Point x="201.66666666666669" y="316.4694787379972" />
			<Point x="186.48148148148147" y="330.55041152263374" />
			<Point x="169.44444444444443" y="344.05521262002753" />
			<Point x="151.66666666666666" y="356.09910836762697" />
			<Point x="134.25925925925927" y="365.79732510288073" />
			<Point x="118.33333333333334" y="372.26508916323735" />
			<Point x="105.0" y="374.61762688614544" />
			<Point x="105.0" y="374.61762688614544" />
			<Point x="96.73696844993138" y="374.45473251028807" />
			<Point x="90.19204389574762" y="373.87002743484226" />
			<Point x="85.2314814814815" y="372.7194787379973" />
			<Point x="81.721536351166" y="370.8590534979424" />
			<Point x="79.52846364883403" y="368.144718792867" />
			<Point x="78.5185185185185" y="364.4324417009603" />
			<Point x="78.5579561042524" y="359.57818930041157" />
			<Point x="79.51303155006858" y="353.4379286694102" />
			<Point x="81.25" y="345.8676268861454" />
			<Point x="81.25" y="345.8676268861454" />
			<Point x="86.70781893004113" y="334.1375171467764" />
			<Point x="96.48662551440331" y="318.97119341563786" />
			<Point x="109.44444444444446" y="301.65466392318245" />
			<Point x="124.43930041152262" y="283.4739368998629" />
			<Point x="140.32921810699588" y="265.71502057613174" />
			<Point x="155.9722222222222" y="249.66392318244178" />
			<Point x="170.22633744855966" y="236.60665294924556" />
			<Point x="181.94958847736623" y="227.82921810699594" />
			<Point x="190.0" y="224.61762688614544" />
			<Point x="190.0" y="224.61762688614544" />
			<Point x="191.65980795610423" y="224.93141289437594" />
			<Point x="193.278463648834" y="225.8316186556927" />
			<Point x="194.81481481481484" y="227.2565157750343" />
			<Point x="196.22770919067213" y="229.14437585733882" />
			<Point x="197.47599451303157" y="231.43347050754457" />
			<Point x="198.51851851851853" y="234.0620713305899" />
			<Point x="199.3141289437586" y="236.96844993141292" />
			<Point x="199.8216735253772" y="240.09087791495202" />
			<Point x="200.0" y="243.36762688614544" />
			<Point x="200.0" y="243.36762688614544" />
			<Point x="200.0" y="243.36762688614544" />
			<Point x="200.0" y="243.36762688614544" />
			<Point x="200.0" y="243.36762688614544" />
			<Point x="200.0" y="243.36762688614544" />
			<Point x="200.0" y="243.36762688614544" />
			<Point x="200.0" y="243.36762688614544" />
			<Point x="200.0" y="243.36762688614544" />
			<Point x="200.0" y="243.36762688614544" />
			<Point x="200.0" y="243.36762688614544" />
		</Stroke>
		<Stroke colour="black">
			<Point x="327.5" y="44.617626886145416" />
			<Point x="317.7366255144033" y="52.23079561042539" />
			<Point x="310.1337448559671" y="59.96742112482856" />
			<Point x="304.72222222222223" y="67.67318244170085" />
			<Point x="301.5329218106996" y="75.19375857338822" />
			<Point x="300.59670781893004" y="82.37482853223597" />
			<Point x="301.94444444444446" y="89.06207133058992" />
			<Point x="305.60699588477365" y="95.10116598079564" />
			<Point x="311.6152263374485" y="100.33779149519894" />
			<Point x="320.0" y="104.61762688614542" />
			<Point x="320.0" y="104.61762688614542" />
			<Point x="331.96159122085044" y="107.32167352537729" />
			<Point x="344.2112482853224" y="106.52777777777779" />
			<Point x="356.29629629629636" y="102.62688614540465" />
			<Point x="367.76406035665303" y="96.00994513031551" />
			<Point x="378.161865569273" y="87.06790123456798" />
			<Point x="387.03703703703707" y="76.1917009602196" />
			<Point x="393.9368998628258" y="63.77229080932793" />
			<Point x="398.4087791495199" y="50.200617283950635" />
			<Point x="400.0" y="35.867626886145416" />
			<Point x="400.0" y="35.867626886145416" />
			<Point x="398.5425240054869" y="30.817901234567987" />
			<Point x="394.45130315500694" y="27.32167352537715" />
			<Point x="388.14814814814815" y="25.35836762688611" />
			<Point x="380.0548696844993" y="24.907407407407476" />
			<Point x="370.5932784636488" y="25.948216735253737" />
			<Point x="360.1851851851851" y="28.460219478738082" />
			<Point x="349.2524005486968" y="32.42283950617292" />
			<Point x="338.2167352537723" y="37.815500685871086" />
			<Point x="327.5" y="44.617626886145416" />
			<Point x="327.5" y="44.617626886145416" />
			<Point x="327.5" y="44.617626886145416" />
			<Point x="327.5" y="44.617626886145416" />
			<Point x="327.5" y="44.617626886145416" />
			<Point x="327.5" y="44.617626886145416" />
			<Point x="327.5" y="44.617626886145416" />
			<Point x="327.5" y="44.617626886145416" />
			<Point x="327.5" y="44.617626886145416" />
			<Point x="327.5" y="44.617626886145416" />
			<Point x="327.5" y="44.617626886145416" />
		</Stroke>
	</StrokeSet>
</WhiteboardCaptureSession>